{
  "symbol": "AVAXUSDT",
  "total_profit_dollars": 24.4803,
  "avg_profit_per_trade": 1.0644,
  "total_trades": 23,
  "wins": 15,
  "losses": 8,
  "win_rate": 65.22,
  "trades": [
    {
      "entry_time": "2025-08-02T16:13:22.425488",
      "entry_price": 21.21,
      "exit_time": "2025-08-02T16:23:23.046602",
      "exit_price": 21.17,
      "qty": 0.940304,
      "entry_value": 19.9438,
      "exit_value": 19.9062,
      "pnl_dollars": -0.0376,
      "pnl_percentage": -0.19
    },
    {
      "entry_time": "2025-08-02T17:23:22.444813",
      "entry_price": 21.26,
      "exit_time": "2025-08-02T17:33:23.102461",
      "exit_price": 21.25,
      "qty": 0.938835,
      "entry_value": 19.9596,
      "exit_value": 19.9502,
      "pnl_dollars": -0.0094,
      "pnl_percentage": -0.05
    },
    {
      "entry_time": "2025-08-02T18:33:22.413931",
      "entry_price": 20.75,
      "exit_time": "2025-08-02T18:43:23.207110",
      "exit_price": 20.77,
      "qty": 0.960419,
      "entry_value": 19.9287,
      "exit_value": 19.9479,
      "pnl_dollars": 0.0192,
      "pnl_percentage": 0.1
    },
    {
      "entry_time": "2025-08-02T20:23:22.406919",
      "entry_price": 20.94,
      "exit_time": "2025-08-02T20:33:22.953929",
      "exit_price": 21.0,
      "qty": 0.949704,
      "entry_value": 19.8868,
      "exit_value": 19.9438,
      "pnl_dollars": 0.057,
      "pnl_percentage": 0.29
    },
    {
      "entry_time": "2025-08-02T21:33:22.435902",
      "entry_price": 20.97,
      "exit_time": "2025-08-02T21:43:23.262933",
      "exit_price": 20.98,
      "qty": 0.952102,
      "entry_value": 19.9656,
      "exit_value": 19.9751,
      "pnl_dollars": 0.0095,
      "pnl_percentage": 0.05
    },
    {
      "entry_time": "2025-08-03T01:53:29.610618",
      "entry_price": 21.05,
      "exit_time": "2025-08-03T01:53:58.247876",
      "exit_price": 21.03,
      "qty": 2.377556,
      "entry_value": 50.0476,
      "exit_value": 50.0,
      "pnl_dollars": -0.0476,
      "pnl_percentage": -0.1
    },
    {
      "entry_time": "2025-08-03T11:37:41.511009",
      "entry_price": 21.36,
      "exit_time": "2025-08-03T11:46:46.486032",
      "exit_price": 21.38,
      "qty": 23.40824,
      "entry_value": 500.0,
      "exit_value": 500.4682,
      "pnl_dollars": 0.4682,
      "pnl_percentage": 0.09
    },
    {
      "entry_time": "2025-08-03T13:17:45.456143",
      "entry_price": 21.42,
      "exit_time": "2025-08-03T13:18:12.984105",
      "exit_price": 21.4,
      "qty": 23.364486,
      "entry_value": 500.4673,
      "exit_value": 500.0,
      "pnl_dollars": -0.4673,
      "pnl_percentage": -0.09
    },
    {
      "entry_time": "2025-08-03T13:59:08.923013",
      "entry_price": 21.37,
      "exit_time": "2025-08-03T14:09:10.136931",
      "exit_price": 21.41,
      "qty": 23.353573,
      "entry_value": 499.0659,
      "exit_value": 500.0,
      "pnl_dollars": 0.9341,
      "pnl_percentage": 0.19
    },
    {
      "entry_time": "2025-08-03T14:59:41.504780",
      "entry_price": 21.34,
      "exit_time": "2025-08-04T02:40:17.183069",
      "exit_price": 21.87,
      "qty": 22.862369,
      "entry_value": 487.883,
      "exit_value": 500.0,
      "pnl_dollars": 12.1171,
      "pnl_percentage": 2.48
    },
    {
      "entry_time": "2025-08-05T05:04:21.715724",
      "entry_price": 22.79,
      "exit_time": "2025-08-05T05:04:51.427013",
      "exit_price": 22.79,
      "qty": 21.939447,
      "entry_value": 500.0,
      "exit_value": 500.0,
      "pnl_dollars": 0.0,
      "pnl_percentage": 0.0
    },
    {
      "entry_time": "2025-08-05T07:35:45.864659",
      "entry_price": 22.27,
      "exit_time": "2025-08-05T10:55:57.526518",
      "exit_price": 22.79,
      "qty": 22.451729,
      "entry_value": 500.0,
      "exit_value": 511.6749,
      "pnl_dollars": 11.6749,
      "pnl_percentage": 2.33
    },
    {
      "entry_time": "2025-08-05T13:05:40.189845",
      "entry_price": 22.33,
      "exit_time": "2025-08-05T13:15:41.001010",
      "exit_price": 22.28,
      "qty": 22.441652,
      "entry_value": 501.1221,
      "exit_value": 500.0,
      "pnl_dollars": -1.1221,
      "pnl_percentage": -0.22
    },
    {
      "entry_time": "2025-08-05T13:45:40.204422",
      "entry_price": 22.38,
      "exit_time": "2025-08-05T13:55:40.863081",
      "exit_price": 22.39,
      "qty": 22.331398,
      "entry_value": 499.7767,
      "exit_value": 500.0,
      "pnl_dollars": 0.2233,
      "pnl_percentage": 0.04
    },
    {
      "entry_time": "2025-08-05T15:36:56.525222",
      "entry_price": 21.67,
      "exit_time": "2025-08-05T15:46:39.814757",
      "exit_price": 21.7,
      "qty": 23.041475,
      "entry_value": 499.3088,
      "exit_value": 500.0,
      "pnl_dollars": 0.6912,
      "pnl_percentage": 0.14
    },
    {
      "entry_time": "2025-08-05T16:06:39.794770",
      "entry_price": 21.81,
      "exit_time": "2025-08-05T16:16:40.638783",
      "exit_price": 21.86,
      "qty": 22.872827,
      "entry_value": 498.8564,
      "exit_value": 500.0,
      "pnl_dollars": 1.1436,
      "pnl_percentage": 0.23
    },
    {
      "entry_time": "2025-08-05T16:56:39.784313",
      "entry_price": 21.79,
      "exit_time": "2025-08-05T16:57:57.881812",
      "exit_price": 21.8,
      "qty": 22.93578,
      "entry_value": 499.7706,
      "exit_value": 500.0,
      "pnl_dollars": 0.2294,
      "pnl_percentage": 0.05
    },
    {
      "entry_time": "2025-08-05T21:36:39.812874",
      "entry_price": 21.75,
      "exit_time": "2025-08-05T21:46:40.428092",
      "exit_price": 21.71,
      "qty": 23.030861,
      "entry_value": 500.9212,
      "exit_value": 500.0,
      "pnl_dollars": -0.9212,
      "pnl_percentage": -0.18
    },
    {
      "entry_time": "2025-08-05T22:16:39.792313",
      "entry_price": 21.7,
      "exit_time": "2025-08-05T22:21:20.959953",
      "exit_price": 21.68,
      "qty": 23.062731,
      "entry_value": 500.4613,
      "exit_value": 500.0,
      "pnl_dollars": -0.4613,
      "pnl_percentage": -0.09
    },
    {
      "entry_time": "2025-08-05T22:51:20.225194",
      "entry_price": 21.77,
      "exit_time": "2025-08-05T22:56:40.395915",
      "exit_price": 21.77,
      "qty": 22.967386,
      "entry_value": 500.0,
      "exit_value": 500.0,
      "pnl_dollars": 0.0,
      "pnl_percentage": 0.0
    },
    {
      "entry_time": "2025-08-05T23:26:39.760152",
      "entry_price": 21.87,
      "exit_time": "2025-08-05T23:36:40.452957",
      "exit_price": 21.88,
      "qty": 22.85192,
      "entry_value": 499.7715,
      "exit_value": 500.0,
      "pnl_dollars": 0.2285,
      "pnl_percentage": 0.05
    },
    {
      "entry_time": "2025-08-06T00:06:49.059406",
      "entry_price": 21.87,
      "exit_time": "2025-08-06T13:14:15.713918",
      "exit_price": 21.87,
      "qty": 22.862369,
      "entry_value": 500.0,
      "exit_value": 500.0,
      "pnl_dollars": 0.0,
      "pnl_percentage": 0.0
    },
    {
      "entry_time": "2025-08-09T03:33:05.477333",
      "entry_price": 24.06,
      "exit_time": "2025-08-09T04:17:37.734675",
      "exit_price": 24.0,
      "qty": 4.155067,
      "entry_value": 99.9709,
      "exit_value": 99.7216,
      "pnl_dollars": -0.2493,
      "pnl_percentage": -0.25
    }
  ]
}