{
  "symbol": "LTCUSDT",
  "total_profit_dollars": 1.534,
  "avg_profit_per_trade": 0.1918,
  "total_trades": 8,
  "wins": 5,
  "losses": 3,
  "win_rate": 62.5,
  "trades": [
    {
      "entry_time": "2025-08-02T16:53:22.433792",
      "entry_price": 106.78,
      "exit_time": "2025-08-02T17:03:23.125503",
      "exit_price": 106.77,
      "qty": 0.18668,
      "entry_value": 19.9337,
      "exit_value": 19.9318,
      "pnl_dollars": -0.0019,
      "pnl_percentage": -0.01
    },
    {
      "entry_time": "2025-08-03T03:06:04.509126",
      "entry_price": 108.39,
      "exit_time": "2025-08-03T03:07:51.480118",
      "exit_price": 108.31,
      "qty": 0.461297,
      "entry_value": 50.0,
      "exit_value": 49.9631,
      "pnl_dollars": -0.0369,
      "pnl_percentage": -0.07
    },
    {
      "entry_time": "2025-08-03T03:37:17.716222",
      "entry_price": 107.23,
      "exit_time": "2025-08-03T03:47:18.262141",
      "exit_price": 107.52,
      "qty": 0.186012,
      "entry_value": 19.9461,
      "exit_value": 20.0,
      "pnl_dollars": 0.0539,
      "pnl_percentage": 0.27
    },
    {
      "entry_time": "2025-08-03T06:51:55.727323",
      "entry_price": 107.85,
      "exit_time": "2025-08-03T07:01:49.081884",
      "exit_price": 108.07,
      "qty": 0.185443,
      "entry_value": 20.0,
      "exit_value": 20.0408,
      "pnl_dollars": 0.0408,
      "pnl_percentage": 0.2
    },
    {
      "entry_time": "2025-08-03T10:46:45.916454",
      "entry_price": 109.12,
      "exit_time": "2025-08-03T10:57:34.920227",
      "exit_price": 109.19,
      "qty": 2.289031,
      "entry_value": 249.7791,
      "exit_value": 249.9393,
      "pnl_dollars": 0.1602,
      "pnl_percentage": 0.06
    },
    {
      "entry_time": "2025-08-04T07:58:50.762222",
      "entry_price": 111.69,
      "exit_time": "2025-08-04T08:01:37.001052",
      "exit_price": 111.48,
      "qty": 0.891791,
      "entry_value": 99.6041,
      "exit_value": 99.4169,
      "pnl_dollars": -0.1873,
      "pnl_percentage": -0.19
    },
    {
      "entry_time": "2025-08-04T09:17:44.211675",
      "entry_price": 111.14,
      "exit_time": "2025-08-04T09:27:34.727511",
      "exit_price": 112.83,
      "qty": 0.880187,
      "entry_value": 97.824,
      "exit_value": 99.3115,
      "pnl_dollars": 1.4875,
      "pnl_percentage": 1.52
    },
    {
      "entry_time": "2025-08-04T09:57:34.405629",
      "entry_price": 112.87,
      "exit_time": "2025-08-04T10:07:34.914883",
      "exit_price": 112.89,
      "qty": 0.880258,
      "entry_value": 99.3547,
      "exit_value": 99.3723,
      "pnl_dollars": 0.0176,
      "pnl_percentage": 0.02
    }
  ]
}